pyfiri/__init__.py
pyfiri/_firi.py
pyfiri/firi.py
pyfiri/_ext/_data/firi2018ed3.nc
pyfiri/_ext/_data/firi2018p182_5v1.nc
pyfiri-2.0.0b0.dist-info/LICENSE.txt
pyfiri-2.0.0b0.dist-info/METADATA
pyfiri-2.0.0b0.dist-info/WHEEL
pyfiri-2.0.0b0.dist-info/top_level.txt
pyfiri-2.0.0b0.dist-info/RECORD
