Metadata-Version: 2.1
Name: pyfiri
Version: 2.0.0b0
Summary: pyFIRI is a Python3 implementation of the FIRI-2018, a semi-empirical model of the non-auroral Earth's ionosphere D-Region.
Home-page: https://bitbucket.org/ozolotov/pyfiri2018/
Author: Oleg Zolotov
Author-email: zolotovo@gmail.com
License: Apache Software License
Keywords: lower ionosphere of the Earth,D-region,D-layer,model,FIRI
Platform: UNKNOWN
Classifier: Development Status :: 4 - Beta
Classifier: Intended Audience :: Science/Research
Classifier: Topic :: Scientific/Engineering :: Physics
Classifier: License :: OSI Approved :: Apache Software License
Classifier: Programming Language :: Python :: 3
Classifier: Programming Language :: Python :: 3.6
Classifier: Programming Language :: Python :: 3.7
Classifier: Programming Language :: Python :: 3.8
Classifier: Programming Language :: Python :: 3.9
Classifier: Programming Language :: Python :: 3 :: Only
License-File: LICENSE.txt
Requires-Dist: scipy
Requires-Dist: xarray
